sapp/__init__.py
sapp/configurator.py
sapp/context.py
sapp/context_manager.py
sapp/decorators.py
sapp/plugin.py
sapp/testing.py
sapp/plugins/__init__.py
sapp/plugins/json.py
sapp/plugins/logging.py
sapp/plugins/redis.py
sapp/plugins/settings.py
sapp/plugins/celery/__init__.py
sapp/plugins/celery/plugin.py
sapp/plugins/pyramid/__init__.py
sapp/plugins/pyramid/configurator.py
sapp/plugins/pyramid/plugins.py
sapp/plugins/pyramid/routing.py
sapp/plugins/pyramid/testing.py
sapp/plugins/pyramid/views.py
sapp/plugins/pyramid/tests/__init__.py
sapp/plugins/pyramid/tests/test_controller.py
sapp/plugins/pyramid/tests/test_plugins.py
sapp/plugins/pyramid/tests/test_pyramid.py
sapp/plugins/pyramid/tests/test_routing.py
sapp/plugins/sqlalchemy/__init__.py
sapp/plugins/sqlalchemy/alembic.py
sapp/plugins/sqlalchemy/database.py
sapp/plugins/sqlalchemy/driver.py
sapp/plugins/sqlalchemy/exceptions.py
sapp/plugins/sqlalchemy/plugin.py
sapp/plugins/sqlalchemy/recreate.py
sapp/plugins/sqlalchemy/testing.py
sapp/plugins/sqlalchemy/tests/__init__.py
sapp/plugins/sqlalchemy/tests/test_alembic.py
sapp/plugins/sqlalchemy/tests/test_database.py
sapp/plugins/sqlalchemy/tests/test_driver.py
sapp/plugins/sqlalchemy/tests/test_exceptions.py
sapp/plugins/sqlalchemy/tests/test_plugin.py
sapp/plugins/sqlalchemy/tests/test_recreate.py
sapp/plugins/tests/__init__.py
sapp/plugins/tests/test_json.py
sapp/plugins/tests/test_logging.py
sapp/plugins/tests/test_redis.py
sapp/plugins/tests/test_settings.py
sapp/plugins/tornado/__init__.py
sapp/plugins/tornado/configurator.py
sapp/plugins/tornado/plugin.py
sapp/tests/__init__.py
sapp/tests/test_configurator.py
sapp/tests/test_context_manager.py
sapp/tests/test_decorator.py
sapp/tests/test_decorators.py
sapp/tests/test_plugin.py
sapp-0.4.dist-info/METADATA
sapp-0.4.dist-info/WHEEL
sapp-0.4.dist-info/top_level.txt
sapp-0.4.dist-info/zip-safe
sapp-0.4.dist-info/RECORD
