Metadata-Version: 2.1
Name: sapp
Version: 0.4
Summary: Simple Application
Home-page: https://github.com/socek/sapp
Author: Dominik "Socek" Długajczyk
Author-email: msocek@gmail.com
License: MIT
Keywords: application,settings
Platform: UNKNOWN
Classifier: Development Status :: 4 - Beta
Classifier: Environment :: Web Environment
Classifier: Intended Audience :: Developers
Classifier: License :: OSI Approved :: MIT License
Classifier: Operating System :: OS Independent
Classifier: Programming Language :: Python
Classifier: Programming Language :: Python :: 3
Classifier: Programming Language :: Python :: 3.6
Classifier: Programming Language :: Python :: 3.7
